microhttp/__init__.py
microhttp/application.py
microhttp/bus.py
microhttp/exceptions.py
microhttp/ext/__init__.py
microhttp/ext/email.py
microhttp/ext/i18n.py
microhttp/ext/log.py
microhttp/ext/template.py
microhttp/ext/db/__init__.py
microhttp/ext/db/database_manager.py
microhttp/tests/__init__.py
microhttp/tests/conftest.py
microhttp/tests/test_application.py
microhttp/tests/test_exceptions.py
microhttp/tests/test_ext_db.py
microhttp/tests/test_ext_email.py
microhttp/tests/test_ext_i18n.py
microhttp/tests/test_ext_log.py
microhttp/tests/test_ext_template.py
microhttp/tests/helpers/__init__.py
microhttp/tests/helpers/smtplib_mock.py
microhttp-0.14.6.dist-info/LICENSE
microhttp-0.14.6.dist-info/METADATA
microhttp-0.14.6.dist-info/WHEEL
microhttp-0.14.6.dist-info/top_level.txt
microhttp-0.14.6.dist-info/RECORD
