Metadata-Version: 2.1
Name: microhttp
Version: 0.14.6
Summary: A tool-chain for creating web application based on nanohttp
Home-page: http://github.com/meyt/microhttp
Author: Mahdi Ghane.g
Author-email: UNKNOWN
License: MIT
Keywords: nanohttp microhttp web tool-chain
Platform: UNKNOWN
Classifier: Development Status :: 3 - Alpha
Classifier: Intended Audience :: Developers
Classifier: License :: OSI Approved :: MIT License
Classifier: Operating System :: POSIX :: Linux
Classifier: Operating System :: Unix
Classifier: Programming Language :: Python :: 3.6
Classifier: Topic :: Software Development :: Libraries
Requires-Dist: nanohttp (==1.11.1)
Requires-Dist: pymlconf (==1.2.*)
Requires-Dist: sqlalchemy
Requires-Dist: mako
